{
  "type": "File",
  "start": 0,
  "end": 2140,
  "loc": {
    "start": {
      "line": 1,
      "column": 0
    },
    "end": {
      "line": 56,
      "column": 0
    }
  },
  "program": {
    "type": "Program",
    "start": 0,
    "end": 2140,
    "loc": {
      "start": {
        "line": 1,
        "column": 0
      },
      "end": {
        "line": 56,
        "column": 0
      }
    },
    "sourceType": "module",
    "body": [
      {
        "type": "ImportDeclaration",
        "start": 1596,
        "end": 1652,
        "loc": {
          "start": {
            "line": 33,
            "column": 0
          },
          "end": {
            "line": 33,
            "column": 56
          }
        },
        "specifiers": [
          {
            "type": "ImportDefaultSpecifier",
            "start": 1603,
            "end": 1618,
            "loc": {
              "start": {
                "line": 33,
                "column": 7
              },
              "end": {
                "line": 33,
                "column": 22
              }
            },
            "local": {
              "type": "Identifier",
              "start": 1603,
              "end": 1618,
              "loc": {
                "start": {
                  "line": 33,
                  "column": 7
                },
                "end": {
                  "line": 33,
                  "column": 22
                },
                "identifierName": "OwnableResource"
              },
              "name": "OwnableResource",
              "leadingComments": null
            },
            "leadingComments": null
          }
        ],
        "source": {
          "type": "StringLiteral",
          "start": 1624,
          "end": 1651,
          "loc": {
            "start": {
              "line": 33,
              "column": 28
            },
            "end": {
              "line": 33,
              "column": 55
            }
          },
          "extra": {
            "rawValue": "../traits/OwnableResource",
            "raw": "'../traits/OwnableResource'"
          },
          "value": "../traits/OwnableResource"
        },
        "leadingComments": [
          {
            "type": "CommentBlock",
            "value": "\n * BSD 3-Clause License\n *\n * Copyright (c) 2017, MapCreator\n * All rights reserved.\n *\n * Redistribution and use in source and binary forms, with or without\n * modification, are permitted provided that the following conditions are met:\n *\n *  Redistributions of source code must retain the above copyright notice, this\n *   list of conditions and the following disclaimer.\n *\n *  Redistributions in binary form must reproduce the above copyright notice,\n *   this list of conditions and the following disclaimer in the documentation\n *   and/or other materials provided with the distribution.\n *\n *  Neither the name of the copyright holder nor the names of its\n *   contributors may be used to endorse or promote products derived from\n *   this software without specific prior written permission.\n *\n * THIS SOFTWARE IS PROVIDED BY THE COPYRIGHT HOLDERS AND CONTRIBUTORS \"AS IS\"\n * AND ANY EXPRESS OR IMPLIED WARRANTIES, INCLUDING, BUT NOT LIMITED TO, THE\n * IMPLIED WARRANTIES OF MERCHANTABILITY AND FITNESS FOR A PARTICULAR PURPOSE ARE\n * DISCLAIMED. IN NO EVENT SHALL THE COPYRIGHT HOLDER OR CONTRIBUTORS BE LIABLE\n * FOR ANY DIRECT, INDIRECT, INCIDENTAL, SPECIAL, EXEMPLARY, OR CONSEQUENTIAL\n * DAMAGES (INCLUDING, BUT NOT LIMITED TO, PROCUREMENT OF SUBSTITUTE GOODS OR\n * SERVICES; LOSS OF USE, DATA, OR PROFITS; OR BUSINESS INTERRUPTION) HOWEVER\n * CAUSED AND ON ANY THEORY OF LIABILITY, WHETHER IN CONTRACT, STRICT LIABILITY,\n * OR TORT (INCLUDING NEGLIGENCE OR OTHERWISE) ARISING IN ANY WAY OUT OF THE USE\n * OF THIS SOFTWARE, EVEN IF ADVISED OF THE POSSIBILITY OF SUCH DAMAGE.\n ",
            "start": 0,
            "end": 1594,
            "loc": {
              "start": {
                "line": 1,
                "column": 0
              },
              "end": {
                "line": 31,
                "column": 3
              }
            }
          }
        ]
      },
      {
        "type": "ImportDeclaration",
        "start": 1653,
        "end": 1692,
        "loc": {
          "start": {
            "line": 34,
            "column": 0
          },
          "end": {
            "line": 34,
            "column": 39
          }
        },
        "specifiers": [
          {
            "type": "ImportDefaultSpecifier",
            "start": 1660,
            "end": 1668,
            "loc": {
              "start": {
                "line": 34,
                "column": 7
              },
              "end": {
                "line": 34,
                "column": 15
              }
            },
            "local": {
              "type": "Identifier",
              "start": 1660,
              "end": 1668,
              "loc": {
                "start": {
                  "line": 34,
                  "column": 7
                },
                "end": {
                  "line": 34,
                  "column": 15
                },
                "identifierName": "CrudBase"
              },
              "name": "CrudBase"
            }
          }
        ],
        "source": {
          "type": "StringLiteral",
          "start": 1674,
          "end": 1691,
          "loc": {
            "start": {
              "line": 34,
              "column": 21
            },
            "end": {
              "line": 34,
              "column": 38
            }
          },
          "extra": {
            "rawValue": "./base/CrudBase",
            "raw": "'./base/CrudBase'"
          },
          "value": "./base/CrudBase"
        }
      },
      {
        "type": "ImportDeclaration",
        "start": 1693,
        "end": 1740,
        "loc": {
          "start": {
            "line": 35,
            "column": 0
          },
          "end": {
            "line": 35,
            "column": 47
          }
        },
        "specifiers": [
          {
            "type": "ImportDefaultSpecifier",
            "start": 1700,
            "end": 1712,
            "loc": {
              "start": {
                "line": 35,
                "column": 7
              },
              "end": {
                "line": 35,
                "column": 19
              }
            },
            "local": {
              "type": "Identifier",
              "start": 1700,
              "end": 1712,
              "loc": {
                "start": {
                  "line": 35,
                  "column": 7
                },
                "end": {
                  "line": 35,
                  "column": 19
                },
                "identifierName": "ImageHandler"
              },
              "name": "ImageHandler"
            }
          }
        ],
        "source": {
          "type": "StringLiteral",
          "start": 1718,
          "end": 1739,
          "loc": {
            "start": {
              "line": 35,
              "column": 25
            },
            "end": {
              "line": 35,
              "column": 46
            }
          },
          "extra": {
            "rawValue": "./base/ImageHandler",
            "raw": "'./base/ImageHandler'"
          },
          "value": "./base/ImageHandler"
        }
      },
      {
        "type": "ImportDeclaration",
        "start": 1741,
        "end": 1781,
        "loc": {
          "start": {
            "line": 36,
            "column": 0
          },
          "end": {
            "line": 36,
            "column": 40
          }
        },
        "specifiers": [
          {
            "type": "ImportSpecifier",
            "start": 1749,
            "end": 1752,
            "loc": {
              "start": {
                "line": 36,
                "column": 8
              },
              "end": {
                "line": 36,
                "column": 11
              }
            },
            "imported": {
              "type": "Identifier",
              "start": 1749,
              "end": 1752,
              "loc": {
                "start": {
                  "line": 36,
                  "column": 8
                },
                "end": {
                  "line": 36,
                  "column": 11
                },
                "identifierName": "mix"
              },
              "name": "mix"
            },
            "local": {
              "type": "Identifier",
              "start": 1749,
              "end": 1752,
              "loc": {
                "start": {
                  "line": 36,
                  "column": 8
                },
                "end": {
                  "line": 36,
                  "column": 11
                },
                "identifierName": "mix"
              },
              "name": "mix"
            }
          }
        ],
        "source": {
          "type": "StringLiteral",
          "start": 1759,
          "end": 1780,
          "loc": {
            "start": {
              "line": 36,
              "column": 18
            },
            "end": {
              "line": 36,
              "column": 39
            }
          },
          "extra": {
            "rawValue": "../utils/reflection",
            "raw": "'../utils/reflection'"
          },
          "value": "../utils/reflection"
        },
        "trailingComments": [
          {
            "type": "CommentBlock",
            "value": "*\n * Layer\n * @extends {CrudBase}\n * @extends {OwnableResource}\n ",
            "start": 1783,
            "end": 1852,
            "loc": {
              "start": {
                "line": 38,
                "column": 0
              },
              "end": {
                "line": 42,
                "column": 3
              }
            }
          }
        ]
      },
      {
        "type": "ExportDefaultDeclaration",
        "start": 1853,
        "end": 2139,
        "loc": {
          "start": {
            "line": 43,
            "column": 0
          },
          "end": {
            "line": 55,
            "column": 1
          }
        },
        "declaration": {
          "type": "ClassDeclaration",
          "start": 1868,
          "end": 2139,
          "loc": {
            "start": {
              "line": 43,
              "column": 15
            },
            "end": {
              "line": 55,
              "column": 1
            }
          },
          "id": {
            "type": "Identifier",
            "start": 1874,
            "end": 1879,
            "loc": {
              "start": {
                "line": 43,
                "column": 21
              },
              "end": {
                "line": 43,
                "column": 26
              },
              "identifierName": "Layer"
            },
            "name": "Layer",
            "leadingComments": null
          },
          "superClass": {
            "type": "CallExpression",
            "start": 1888,
            "end": 1918,
            "loc": {
              "start": {
                "line": 43,
                "column": 35
              },
              "end": {
                "line": 43,
                "column": 65
              }
            },
            "callee": {
              "type": "Identifier",
              "start": 1888,
              "end": 1891,
              "loc": {
                "start": {
                  "line": 43,
                  "column": 35
                },
                "end": {
                  "line": 43,
                  "column": 38
                },
                "identifierName": "mix"
              },
              "name": "mix"
            },
            "arguments": [
              {
                "type": "Identifier",
                "start": 1892,
                "end": 1900,
                "loc": {
                  "start": {
                    "line": 43,
                    "column": 39
                  },
                  "end": {
                    "line": 43,
                    "column": 47
                  },
                  "identifierName": "CrudBase"
                },
                "name": "CrudBase"
              },
              {
                "type": "Identifier",
                "start": 1902,
                "end": 1917,
                "loc": {
                  "start": {
                    "line": 43,
                    "column": 49
                  },
                  "end": {
                    "line": 43,
                    "column": 64
                  },
                  "identifierName": "OwnableResource"
                },
                "name": "OwnableResource"
              }
            ]
          },
          "body": {
            "type": "ClassBody",
            "start": 1919,
            "end": 2139,
            "loc": {
              "start": {
                "line": 43,
                "column": 66
              },
              "end": {
                "line": 55,
                "column": 1
              }
            },
            "body": [
              {
                "type": "ClassMethod",
                "start": 2019,
                "end": 2088,
                "loc": {
                  "start": {
                    "line": 48,
                    "column": 2
                  },
                  "end": {
                    "line": 50,
                    "column": 3
                  }
                },
                "computed": false,
                "key": {
                  "type": "Identifier",
                  "start": 2023,
                  "end": 2035,
                  "loc": {
                    "start": {
                      "line": 48,
                      "column": 6
                    },
                    "end": {
                      "line": 48,
                      "column": 18
                    },
                    "identifierName": "imageHandler"
                  },
                  "name": "imageHandler"
                },
                "static": false,
                "kind": "get",
                "id": null,
                "generator": false,
                "expression": false,
                "async": false,
                "params": [],
                "body": {
                  "type": "BlockStatement",
                  "start": 2038,
                  "end": 2088,
                  "loc": {
                    "start": {
                      "line": 48,
                      "column": 21
                    },
                    "end": {
                      "line": 50,
                      "column": 3
                    }
                  },
                  "body": [
                    {
                      "type": "ReturnStatement",
                      "start": 2044,
                      "end": 2084,
                      "loc": {
                        "start": {
                          "line": 49,
                          "column": 4
                        },
                        "end": {
                          "line": 49,
                          "column": 44
                        }
                      },
                      "argument": {
                        "type": "NewExpression",
                        "start": 2051,
                        "end": 2083,
                        "loc": {
                          "start": {
                            "line": 49,
                            "column": 11
                          },
                          "end": {
                            "line": 49,
                            "column": 43
                          }
                        },
                        "callee": {
                          "type": "Identifier",
                          "start": 2055,
                          "end": 2067,
                          "loc": {
                            "start": {
                              "line": 49,
                              "column": 15
                            },
                            "end": {
                              "line": 49,
                              "column": 27
                            },
                            "identifierName": "ImageHandler"
                          },
                          "name": "ImageHandler"
                        },
                        "arguments": [
                          {
                            "type": "MemberExpression",
                            "start": 2068,
                            "end": 2076,
                            "loc": {
                              "start": {
                                "line": 49,
                                "column": 28
                              },
                              "end": {
                                "line": 49,
                                "column": 36
                              }
                            },
                            "object": {
                              "type": "ThisExpression",
                              "start": 2068,
                              "end": 2072,
                              "loc": {
                                "start": {
                                  "line": 49,
                                  "column": 28
                                },
                                "end": {
                                  "line": 49,
                                  "column": 32
                                }
                              }
                            },
                            "property": {
                              "type": "Identifier",
                              "start": 2073,
                              "end": 2076,
                              "loc": {
                                "start": {
                                  "line": 49,
                                  "column": 33
                                },
                                "end": {
                                  "line": 49,
                                  "column": 36
                                },
                                "identifierName": "api"
                              },
                              "name": "api"
                            },
                            "computed": false
                          },
                          {
                            "type": "ThisExpression",
                            "start": 2078,
                            "end": 2082,
                            "loc": {
                              "start": {
                                "line": 49,
                                "column": 38
                              },
                              "end": {
                                "line": 49,
                                "column": 42
                              }
                            }
                          }
                        ]
                      }
                    }
                  ],
                  "directives": []
                },
                "leadingComments": [
                  {
                    "type": "CommentBlock",
                    "value": "*\n   * Handler for item image management\n   * @returns {ImageHandler} - Image handler\n   ",
                    "start": 1923,
                    "end": 2016,
                    "loc": {
                      "start": {
                        "line": 44,
                        "column": 2
                      },
                      "end": {
                        "line": 47,
                        "column": 5
                      }
                    }
                  }
                ]
              },
              {
                "type": "ClassMethod",
                "start": 2092,
                "end": 2137,
                "loc": {
                  "start": {
                    "line": 52,
                    "column": 2
                  },
                  "end": {
                    "line": 54,
                    "column": 3
                  }
                },
                "computed": false,
                "key": {
                  "type": "Identifier",
                  "start": 2096,
                  "end": 2108,
                  "loc": {
                    "start": {
                      "line": 52,
                      "column": 6
                    },
                    "end": {
                      "line": 52,
                      "column": 18
                    },
                    "identifierName": "resourceName"
                  },
                  "name": "resourceName"
                },
                "static": false,
                "kind": "get",
                "id": null,
                "generator": false,
                "expression": false,
                "async": false,
                "params": [],
                "body": {
                  "type": "BlockStatement",
                  "start": 2111,
                  "end": 2137,
                  "loc": {
                    "start": {
                      "line": 52,
                      "column": 21
                    },
                    "end": {
                      "line": 54,
                      "column": 3
                    }
                  },
                  "body": [
                    {
                      "type": "ReturnStatement",
                      "start": 2117,
                      "end": 2133,
                      "loc": {
                        "start": {
                          "line": 53,
                          "column": 4
                        },
                        "end": {
                          "line": 53,
                          "column": 20
                        }
                      },
                      "argument": {
                        "type": "StringLiteral",
                        "start": 2124,
                        "end": 2132,
                        "loc": {
                          "start": {
                            "line": 53,
                            "column": 11
                          },
                          "end": {
                            "line": 53,
                            "column": 19
                          }
                        },
                        "extra": {
                          "rawValue": "layers",
                          "raw": "'layers'"
                        },
                        "value": "layers"
                      }
                    }
                  ],
                  "directives": []
                }
              }
            ]
          },
          "leadingComments": [
            {
              "type": "CommentBlock",
              "value": "*\n * Layer\n * @extends {CrudBase}\n * @extends {OwnableResource}\n ",
              "start": 1783,
              "end": 1852,
              "loc": {
                "start": {
                  "line": 38,
                  "column": 0
                },
                "end": {
                  "line": 42,
                  "column": 3
                }
              }
            }
          ],
          "trailingComments": []
        },
        "leadingComments": [
          {
            "type": "CommentBlock",
            "value": "*\n * Layer\n * @extends {CrudBase}\n * @extends {OwnableResource}\n ",
            "start": 1783,
            "end": 1852,
            "loc": {
              "start": {
                "line": 38,
                "column": 0
              },
              "end": {
                "line": 42,
                "column": 3
              }
            }
          }
        ]
      }
    ],
    "directives": []
  },
  "comments": [
    {
      "type": "CommentBlock",
      "value": "\n * BSD 3-Clause License\n *\n * Copyright (c) 2017, MapCreator\n * All rights reserved.\n *\n * Redistribution and use in source and binary forms, with or without\n * modification, are permitted provided that the following conditions are met:\n *\n *  Redistributions of source code must retain the above copyright notice, this\n *   list of conditions and the following disclaimer.\n *\n *  Redistributions in binary form must reproduce the above copyright notice,\n *   this list of conditions and the following disclaimer in the documentation\n *   and/or other materials provided with the distribution.\n *\n *  Neither the name of the copyright holder nor the names of its\n *   contributors may be used to endorse or promote products derived from\n *   this software without specific prior written permission.\n *\n * THIS SOFTWARE IS PROVIDED BY THE COPYRIGHT HOLDERS AND CONTRIBUTORS \"AS IS\"\n * AND ANY EXPRESS OR IMPLIED WARRANTIES, INCLUDING, BUT NOT LIMITED TO, THE\n * IMPLIED WARRANTIES OF MERCHANTABILITY AND FITNESS FOR A PARTICULAR PURPOSE ARE\n * DISCLAIMED. IN NO EVENT SHALL THE COPYRIGHT HOLDER OR CONTRIBUTORS BE LIABLE\n * FOR ANY DIRECT, INDIRECT, INCIDENTAL, SPECIAL, EXEMPLARY, OR CONSEQUENTIAL\n * DAMAGES (INCLUDING, BUT NOT LIMITED TO, PROCUREMENT OF SUBSTITUTE GOODS OR\n * SERVICES; LOSS OF USE, DATA, OR PROFITS; OR BUSINESS INTERRUPTION) HOWEVER\n * CAUSED AND ON ANY THEORY OF LIABILITY, WHETHER IN CONTRACT, STRICT LIABILITY,\n * OR TORT (INCLUDING NEGLIGENCE OR OTHERWISE) ARISING IN ANY WAY OUT OF THE USE\n * OF THIS SOFTWARE, EVEN IF ADVISED OF THE POSSIBILITY OF SUCH DAMAGE.\n ",
      "start": 0,
      "end": 1594,
      "loc": {
        "start": {
          "line": 1,
          "column": 0
        },
        "end": {
          "line": 31,
          "column": 3
        }
      }
    },
    {
      "type": "CommentBlock",
      "value": "*\n * Layer\n * @extends {CrudBase}\n * @extends {OwnableResource}\n ",
      "start": 1783,
      "end": 1852,
      "loc": {
        "start": {
          "line": 38,
          "column": 0
        },
        "end": {
          "line": 42,
          "column": 3
        }
      }
    },
    {
      "type": "CommentBlock",
      "value": "*\n   * Handler for item image management\n   * @returns {ImageHandler} - Image handler\n   ",
      "start": 1923,
      "end": 2016,
      "loc": {
        "start": {
          "line": 44,
          "column": 2
        },
        "end": {
          "line": 47,
          "column": 5
        }
      }
    }
  ],
  "tokens": [
    {
      "type": "CommentBlock",
      "value": "\n * BSD 3-Clause License\n *\n * Copyright (c) 2017, MapCreator\n * All rights reserved.\n *\n * Redistribution and use in source and binary forms, with or without\n * modification, are permitted provided that the following conditions are met:\n *\n *  Redistributions of source code must retain the above copyright notice, this\n *   list of conditions and the following disclaimer.\n *\n *  Redistributions in binary form must reproduce the above copyright notice,\n *   this list of conditions and the following disclaimer in the documentation\n *   and/or other materials provided with the distribution.\n *\n *  Neither the name of the copyright holder nor the names of its\n *   contributors may be used to endorse or promote products derived from\n *   this software without specific prior written permission.\n *\n * THIS SOFTWARE IS PROVIDED BY THE COPYRIGHT HOLDERS AND CONTRIBUTORS \"AS IS\"\n * AND ANY EXPRESS OR IMPLIED WARRANTIES, INCLUDING, BUT NOT LIMITED TO, THE\n * IMPLIED WARRANTIES OF MERCHANTABILITY AND FITNESS FOR A PARTICULAR PURPOSE ARE\n * DISCLAIMED. IN NO EVENT SHALL THE COPYRIGHT HOLDER OR CONTRIBUTORS BE LIABLE\n * FOR ANY DIRECT, INDIRECT, INCIDENTAL, SPECIAL, EXEMPLARY, OR CONSEQUENTIAL\n * DAMAGES (INCLUDING, BUT NOT LIMITED TO, PROCUREMENT OF SUBSTITUTE GOODS OR\n * SERVICES; LOSS OF USE, DATA, OR PROFITS; OR BUSINESS INTERRUPTION) HOWEVER\n * CAUSED AND ON ANY THEORY OF LIABILITY, WHETHER IN CONTRACT, STRICT LIABILITY,\n * OR TORT (INCLUDING NEGLIGENCE OR OTHERWISE) ARISING IN ANY WAY OUT OF THE USE\n * OF THIS SOFTWARE, EVEN IF ADVISED OF THE POSSIBILITY OF SUCH DAMAGE.\n ",
      "start": 0,
      "end": 1594,
      "loc": {
        "start": {
          "line": 1,
          "column": 0
        },
        "end": {
          "line": 31,
          "column": 3
        }
      }
    },
    {
      "type": {
        "label": "import",
        "keyword": "import",
        "beforeExpr": false,
        "startsExpr": false,
        "rightAssociative": false,
        "isLoop": false,
        "isAssign": false,
        "prefix": false,
        "postfix": false,
        "binop": null,
        "updateContext": null
      },
      "value": "import",
      "start": 1596,
      "end": 1602,
      "loc": {
        "start": {
          "line": 33,
          "column": 0
        },
        "end": {
          "line": 33,
          "column": 6
        }
      }
    },
    {
      "type": {
        "label": "name",
        "beforeExpr": false,
        "startsExpr": true,
        "rightAssociative": false,
        "isLoop": false,
        "isAssign": false,
        "prefix": false,
        "postfix": false,
        "binop": null
      },
      "value": "OwnableResource",
      "start": 1603,
      "end": 1618,
      "loc": {
        "start": {
          "line": 33,
          "column": 7
        },
        "end": {
          "line": 33,
          "column": 22
        }
      }
    },
    {
      "type": {
        "label": "name",
        "beforeExpr": false,
        "startsExpr": true,
        "rightAssociative": false,
        "isLoop": false,
        "isAssign": false,
        "prefix": false,
        "postfix": false,
        "binop": null
      },
      "value": "from",
      "start": 1619,
      "end": 1623,
      "loc": {
        "start": {
          "line": 33,
          "column": 23
        },
        "end": {
          "line": 33,
          "column": 27
        }
      }
    },
    {
      "type": {
        "label": "string",
        "beforeExpr": false,
        "startsExpr": true,
        "rightAssociative": false,
        "isLoop": false,
        "isAssign": false,
        "prefix": false,
        "postfix": false,
        "binop": null,
        "updateContext": null
      },
      "value": "../traits/OwnableResource",
      "start": 1624,
      "end": 1651,
      "loc": {
        "start": {
          "line": 33,
          "column": 28
        },
        "end": {
          "line": 33,
          "column": 55
        }
      }
    },
    {
      "type": {
        "label": ";",
        "beforeExpr": true,
        "startsExpr": false,
        "rightAssociative": false,
        "isLoop": false,
        "isAssign": false,
        "prefix": false,
        "postfix": false,
        "binop": null,
        "updateContext": null
      },
      "start": 1651,
      "end": 1652,
      "loc": {
        "start": {
          "line": 33,
          "column": 55
        },
        "end": {
          "line": 33,
          "column": 56
        }
      }
    },
    {
      "type": {
        "label": "import",
        "keyword": "import",
        "beforeExpr": false,
        "startsExpr": false,
        "rightAssociative": false,
        "isLoop": false,
        "isAssign": false,
        "prefix": false,
        "postfix": false,
        "binop": null,
        "updateContext": null
      },
      "value": "import",
      "start": 1653,
      "end": 1659,
      "loc": {
        "start": {
          "line": 34,
          "column": 0
        },
        "end": {
          "line": 34,
          "column": 6
        }
      }
    },
    {
      "type": {
        "label": "name",
        "beforeExpr": false,
        "startsExpr": true,
        "rightAssociative": false,
        "isLoop": false,
        "isAssign": false,
        "prefix": false,
        "postfix": false,
        "binop": null
      },
      "value": "CrudBase",
      "start": 1660,
      "end": 1668,
      "loc": {
        "start": {
          "line": 34,
          "column": 7
        },
        "end": {
          "line": 34,
          "column": 15
        }
      }
    },
    {
      "type": {
        "label": "name",
        "beforeExpr": false,
        "startsExpr": true,
        "rightAssociative": false,
        "isLoop": false,
        "isAssign": false,
        "prefix": false,
        "postfix": false,
        "binop": null
      },
      "value": "from",
      "start": 1669,
      "end": 1673,
      "loc": {
        "start": {
          "line": 34,
          "column": 16
        },
        "end": {
          "line": 34,
          "column": 20
        }
      }
    },
    {
      "type": {
        "label": "string",
        "beforeExpr": false,
        "startsExpr": true,
        "rightAssociative": false,
        "isLoop": false,
        "isAssign": false,
        "prefix": false,
        "postfix": false,
        "binop": null,
        "updateContext": null
      },
      "value": "./base/CrudBase",
      "start": 1674,
      "end": 1691,
      "loc": {
        "start": {
          "line": 34,
          "column": 21
        },
        "end": {
          "line": 34,
          "column": 38
        }
      }
    },
    {
      "type": {
        "label": ";",
        "beforeExpr": true,
        "startsExpr": false,
        "rightAssociative": false,
        "isLoop": false,
        "isAssign": false,
        "prefix": false,
        "postfix": false,
        "binop": null,
        "updateContext": null
      },
      "start": 1691,
      "end": 1692,
      "loc": {
        "start": {
          "line": 34,
          "column": 38
        },
        "end": {
          "line": 34,
          "column": 39
        }
      }
    },
    {
      "type": {
        "label": "import",
        "keyword": "import",
        "beforeExpr": false,
        "startsExpr": false,
        "rightAssociative": false,
        "isLoop": false,
        "isAssign": false,
        "prefix": false,
        "postfix": false,
        "binop": null,
        "updateContext": null
      },
      "value": "import",
      "start": 1693,
      "end": 1699,
      "loc": {
        "start": {
          "line": 35,
          "column": 0
        },
        "end": {
          "line": 35,
          "column": 6
        }
      }
    },
    {
      "type": {
        "label": "name",
        "beforeExpr": false,
        "startsExpr": true,
        "rightAssociative": false,
        "isLoop": false,
        "isAssign": false,
        "prefix": false,
        "postfix": false,
        "binop": null
      },
      "value": "ImageHandler",
      "start": 1700,
      "end": 1712,
      "loc": {
        "start": {
          "line": 35,
          "column": 7
        },
        "end": {
          "line": 35,
          "column": 19
        }
      }
    },
    {
      "type": {
        "label": "name",
        "beforeExpr": false,
        "startsExpr": true,
        "rightAssociative": false,
        "isLoop": false,
        "isAssign": false,
        "prefix": false,
        "postfix": false,
        "binop": null
      },
      "value": "from",
      "start": 1713,
      "end": 1717,
      "loc": {
        "start": {
          "line": 35,
          "column": 20
        },
        "end": {
          "line": 35,
          "column": 24
        }
      }
    },
    {
      "type": {
        "label": "string",
        "beforeExpr": false,
        "startsExpr": true,
        "rightAssociative": false,
        "isLoop": false,
        "isAssign": false,
        "prefix": false,
        "postfix": false,
        "binop": null,
        "updateContext": null
      },
      "value": "./base/ImageHandler",
      "start": 1718,
      "end": 1739,
      "loc": {
        "start": {
          "line": 35,
          "column": 25
        },
        "end": {
          "line": 35,
          "column": 46
        }
      }
    },
    {
      "type": {
        "label": ";",
        "beforeExpr": true,
        "startsExpr": false,
        "rightAssociative": false,
        "isLoop": false,
        "isAssign": false,
        "prefix": false,
        "postfix": false,
        "binop": null,
        "updateContext": null
      },
      "start": 1739,
      "end": 1740,
      "loc": {
        "start": {
          "line": 35,
          "column": 46
        },
        "end": {
          "line": 35,
          "column": 47
        }
      }
    },
    {
      "type": {
        "label": "import",
        "keyword": "import",
        "beforeExpr": false,
        "startsExpr": false,
        "rightAssociative": false,
        "isLoop": false,
        "isAssign": false,
        "prefix": false,
        "postfix": false,
        "binop": null,
        "updateContext": null
      },
      "value": "import",
      "start": 1741,
      "end": 1747,
      "loc": {
        "start": {
          "line": 36,
          "column": 0
        },
        "end": {
          "line": 36,
          "column": 6
        }
      }
    },
    {
      "type": {
        "label": "{",
        "beforeExpr": true,
        "startsExpr": true,
        "rightAssociative": false,
        "isLoop": false,
        "isAssign": false,
        "prefix": false,
        "postfix": false,
        "binop": null
      },
      "start": 1748,
      "end": 1749,
      "loc": {
        "start": {
          "line": 36,
          "column": 7
        },
        "end": {
          "line": 36,
          "column": 8
        }
      }
    },
    {
      "type": {
        "label": "name",
        "beforeExpr": false,
        "startsExpr": true,
        "rightAssociative": false,
        "isLoop": false,
        "isAssign": false,
        "prefix": false,
        "postfix": false,
        "binop": null
      },
      "value": "mix",
      "start": 1749,
      "end": 1752,
      "loc": {
        "start": {
          "line": 36,
          "column": 8
        },
        "end": {
          "line": 36,
          "column": 11
        }
      }
    },
    {
      "type": {
        "label": "}",
        "beforeExpr": false,
        "startsExpr": false,
        "rightAssociative": false,
        "isLoop": false,
        "isAssign": false,
        "prefix": false,
        "postfix": false,
        "binop": null
      },
      "start": 1752,
      "end": 1753,
      "loc": {
        "start": {
          "line": 36,
          "column": 11
        },
        "end": {
          "line": 36,
          "column": 12
        }
      }
    },
    {
      "type": {
        "label": "name",
        "beforeExpr": false,
        "startsExpr": true,
        "rightAssociative": false,
        "isLoop": false,
        "isAssign": false,
        "prefix": false,
        "postfix": false,
        "binop": null
      },
      "value": "from",
      "start": 1754,
      "end": 1758,
      "loc": {
        "start": {
          "line": 36,
          "column": 13
        },
        "end": {
          "line": 36,
          "column": 17
        }
      }
    },
    {
      "type": {
        "label": "string",
        "beforeExpr": false,
        "startsExpr": true,
        "rightAssociative": false,
        "isLoop": false,
        "isAssign": false,
        "prefix": false,
        "postfix": false,
        "binop": null,
        "updateContext": null
      },
      "value": "../utils/reflection",
      "start": 1759,
      "end": 1780,
      "loc": {
        "start": {
          "line": 36,
          "column": 18
        },
        "end": {
          "line": 36,
          "column": 39
        }
      }
    },
    {
      "type": {
        "label": ";",
        "beforeExpr": true,
        "startsExpr": false,
        "rightAssociative": false,
        "isLoop": false,
        "isAssign": false,
        "prefix": false,
        "postfix": false,
        "binop": null,
        "updateContext": null
      },
      "start": 1780,
      "end": 1781,
      "loc": {
        "start": {
          "line": 36,
          "column": 39
        },
        "end": {
          "line": 36,
          "column": 40
        }
      }
    },
    {
      "type": "CommentBlock",
      "value": "*\n * Layer\n * @extends {CrudBase}\n * @extends {OwnableResource}\n ",
      "start": 1783,
      "end": 1852,
      "loc": {
        "start": {
          "line": 38,
          "column": 0
        },
        "end": {
          "line": 42,
          "column": 3
        }
      }
    },
    {
      "type": {
        "label": "export",
        "keyword": "export",
        "beforeExpr": false,
        "startsExpr": false,
        "rightAssociative": false,
        "isLoop": false,
        "isAssign": false,
        "prefix": false,
        "postfix": false,
        "binop": null,
        "updateContext": null
      },
      "value": "export",
      "start": 1853,
      "end": 1859,
      "loc": {
        "start": {
          "line": 43,
          "column": 0
        },
        "end": {
          "line": 43,
          "column": 6
        }
      }
    },
    {
      "type": {
        "label": "default",
        "keyword": "default",
        "beforeExpr": true,
        "startsExpr": false,
        "rightAssociative": false,
        "isLoop": false,
        "isAssign": false,
        "prefix": false,
        "postfix": false,
        "binop": null,
        "updateContext": null
      },
      "value": "default",
      "start": 1860,
      "end": 1867,
      "loc": {
        "start": {
          "line": 43,
          "column": 7
        },
        "end": {
          "line": 43,
          "column": 14
        }
      }
    },
    {
      "type": {
        "label": "class",
        "keyword": "class",
        "beforeExpr": false,
        "startsExpr": false,
        "rightAssociative": false,
        "isLoop": false,
        "isAssign": false,
        "prefix": false,
        "postfix": false,
        "binop": null,
        "updateContext": null
      },
      "value": "class",
      "start": 1868,
      "end": 1873,
      "loc": {
        "start": {
          "line": 43,
          "column": 15
        },
        "end": {
          "line": 43,
          "column": 20
        }
      }
    },
    {
      "type": {
        "label": "name",
        "beforeExpr": false,
        "startsExpr": true,
        "rightAssociative": false,
        "isLoop": false,
        "isAssign": false,
        "prefix": false,
        "postfix": false,
        "binop": null
      },
      "value": "Layer",
      "start": 1874,
      "end": 1879,
      "loc": {
        "start": {
          "line": 43,
          "column": 21
        },
        "end": {
          "line": 43,
          "column": 26
        }
      }
    },
    {
      "type": {
        "label": "extends",
        "keyword": "extends",
        "beforeExpr": true,
        "startsExpr": false,
        "rightAssociative": false,
        "isLoop": false,
        "isAssign": false,
        "prefix": false,
        "postfix": false,
        "binop": null,
        "updateContext": null
      },
      "value": "extends",
      "start": 1880,
      "end": 1887,
      "loc": {
        "start": {
          "line": 43,
          "column": 27
        },
        "end": {
          "line": 43,
          "column": 34
        }
      }
    },
    {
      "type": {
        "label": "name",
        "beforeExpr": false,
        "startsExpr": true,
        "rightAssociative": false,
        "isLoop": false,
        "isAssign": false,
        "prefix": false,
        "postfix": false,
        "binop": null
      },
      "value": "mix",
      "start": 1888,
      "end": 1891,
      "loc": {
        "start": {
          "line": 43,
          "column": 35
        },
        "end": {
          "line": 43,
          "column": 38
        }
      }
    },
    {
      "type": {
        "label": "(",
        "beforeExpr": true,
        "startsExpr": true,
        "rightAssociative": false,
        "isLoop": false,
        "isAssign": false,
        "prefix": false,
        "postfix": false,
        "binop": null
      },
      "start": 1891,
      "end": 1892,
      "loc": {
        "start": {
          "line": 43,
          "column": 38
        },
        "end": {
          "line": 43,
          "column": 39
        }
      }
    },
    {
      "type": {
        "label": "name",
        "beforeExpr": false,
        "startsExpr": true,
        "rightAssociative": false,
        "isLoop": false,
        "isAssign": false,
        "prefix": false,
        "postfix": false,
        "binop": null
      },
      "value": "CrudBase",
      "start": 1892,
      "end": 1900,
      "loc": {
        "start": {
          "line": 43,
          "column": 39
        },
        "end": {
          "line": 43,
          "column": 47
        }
      }
    },
    {
      "type": {
        "label": ",",
        "beforeExpr": true,
        "startsExpr": false,
        "rightAssociative": false,
        "isLoop": false,
        "isAssign": false,
        "prefix": false,
        "postfix": false,
        "binop": null,
        "updateContext": null
      },
      "start": 1900,
      "end": 1901,
      "loc": {
        "start": {
          "line": 43,
          "column": 47
        },
        "end": {
          "line": 43,
          "column": 48
        }
      }
    },
    {
      "type": {
        "label": "name",
        "beforeExpr": false,
        "startsExpr": true,
        "rightAssociative": false,
        "isLoop": false,
        "isAssign": false,
        "prefix": false,
        "postfix": false,
        "binop": null
      },
      "value": "OwnableResource",
      "start": 1902,
      "end": 1917,
      "loc": {
        "start": {
          "line": 43,
          "column": 49
        },
        "end": {
          "line": 43,
          "column": 64
        }
      }
    },
    {
      "type": {
        "label": ")",
        "beforeExpr": false,
        "startsExpr": false,
        "rightAssociative": false,
        "isLoop": false,
        "isAssign": false,
        "prefix": false,
        "postfix": false,
        "binop": null
      },
      "start": 1917,
      "end": 1918,
      "loc": {
        "start": {
          "line": 43,
          "column": 64
        },
        "end": {
          "line": 43,
          "column": 65
        }
      }
    },
    {
      "type": {
        "label": "{",
        "beforeExpr": true,
        "startsExpr": true,
        "rightAssociative": false,
        "isLoop": false,
        "isAssign": false,
        "prefix": false,
        "postfix": false,
        "binop": null
      },
      "start": 1919,
      "end": 1920,
      "loc": {
        "start": {
          "line": 43,
          "column": 66
        },
        "end": {
          "line": 43,
          "column": 67
        }
      }
    },
    {
      "type": "CommentBlock",
      "value": "*\n   * Handler for item image management\n   * @returns {ImageHandler} - Image handler\n   ",
      "start": 1923,
      "end": 2016,
      "loc": {
        "start": {
          "line": 44,
          "column": 2
        },
        "end": {
          "line": 47,
          "column": 5
        }
      }
    },
    {
      "type": {
        "label": "name",
        "beforeExpr": false,
        "startsExpr": true,
        "rightAssociative": false,
        "isLoop": false,
        "isAssign": false,
        "prefix": false,
        "postfix": false,
        "binop": null
      },
      "value": "get",
      "start": 2019,
      "end": 2022,
      "loc": {
        "start": {
          "line": 48,
          "column": 2
        },
        "end": {
          "line": 48,
          "column": 5
        }
      }
    },
    {
      "type": {
        "label": "name",
        "beforeExpr": false,
        "startsExpr": true,
        "rightAssociative": false,
        "isLoop": false,
        "isAssign": false,
        "prefix": false,
        "postfix": false,
        "binop": null
      },
      "value": "imageHandler",
      "start": 2023,
      "end": 2035,
      "loc": {
        "start": {
          "line": 48,
          "column": 6
        },
        "end": {
          "line": 48,
          "column": 18
        }
      }
    },
    {
      "type": {
        "label": "(",
        "beforeExpr": true,
        "startsExpr": true,
        "rightAssociative": false,
        "isLoop": false,
        "isAssign": false,
        "prefix": false,
        "postfix": false,
        "binop": null
      },
      "start": 2035,
      "end": 2036,
      "loc": {
        "start": {
          "line": 48,
          "column": 18
        },
        "end": {
          "line": 48,
          "column": 19
        }
      }
    },
    {
      "type": {
        "label": ")",
        "beforeExpr": false,
        "startsExpr": false,
        "rightAssociative": false,
        "isLoop": false,
        "isAssign": false,
        "prefix": false,
        "postfix": false,
        "binop": null
      },
      "start": 2036,
      "end": 2037,
      "loc": {
        "start": {
          "line": 48,
          "column": 19
        },
        "end": {
          "line": 48,
          "column": 20
        }
      }
    },
    {
      "type": {
        "label": "{",
        "beforeExpr": true,
        "startsExpr": true,
        "rightAssociative": false,
        "isLoop": false,
        "isAssign": false,
        "prefix": false,
        "postfix": false,
        "binop": null
      },
      "start": 2038,
      "end": 2039,
      "loc": {
        "start": {
          "line": 48,
          "column": 21
        },
        "end": {
          "line": 48,
          "column": 22
        }
      }
    },
    {
      "type": {
        "label": "return",
        "keyword": "return",
        "beforeExpr": true,
        "startsExpr": false,
        "rightAssociative": false,
        "isLoop": false,
        "isAssign": false,
        "prefix": false,
        "postfix": false,
        "binop": null,
        "updateContext": null
      },
      "value": "return",
      "start": 2044,
      "end": 2050,
      "loc": {
        "start": {
          "line": 49,
          "column": 4
        },
        "end": {
          "line": 49,
          "column": 10
        }
      }
    },
    {
      "type": {
        "label": "new",
        "keyword": "new",
        "beforeExpr": true,
        "startsExpr": true,
        "rightAssociative": false,
        "isLoop": false,
        "isAssign": false,
        "prefix": false,
        "postfix": false,
        "binop": null,
        "updateContext": null
      },
      "value": "new",
      "start": 2051,
      "end": 2054,
      "loc": {
        "start": {
          "line": 49,
          "column": 11
        },
        "end": {
          "line": 49,
          "column": 14
        }
      }
    },
    {
      "type": {
        "label": "name",
        "beforeExpr": false,
        "startsExpr": true,
        "rightAssociative": false,
        "isLoop": false,
        "isAssign": false,
        "prefix": false,
        "postfix": false,
        "binop": null
      },
      "value": "ImageHandler",
      "start": 2055,
      "end": 2067,
      "loc": {
        "start": {
          "line": 49,
          "column": 15
        },
        "end": {
          "line": 49,
          "column": 27
        }
      }
    },
    {
      "type": {
        "label": "(",
        "beforeExpr": true,
        "startsExpr": true,
        "rightAssociative": false,
        "isLoop": false,
        "isAssign": false,
        "prefix": false,
        "postfix": false,
        "binop": null
      },
      "start": 2067,
      "end": 2068,
      "loc": {
        "start": {
          "line": 49,
          "column": 27
        },
        "end": {
          "line": 49,
          "column": 28
        }
      }
    },
    {
      "type": {
        "label": "this",
        "keyword": "this",
        "beforeExpr": false,
        "startsExpr": true,
        "rightAssociative": false,
        "isLoop": false,
        "isAssign": false,
        "prefix": false,
        "postfix": false,
        "binop": null,
        "updateContext": null
      },
      "value": "this",
      "start": 2068,
      "end": 2072,
      "loc": {
        "start": {
          "line": 49,
          "column": 28
        },
        "end": {
          "line": 49,
          "column": 32
        }
      }
    },
    {
      "type": {
        "label": ".",
        "beforeExpr": false,
        "startsExpr": false,
        "rightAssociative": false,
        "isLoop": false,
        "isAssign": false,
        "prefix": false,
        "postfix": false,
        "binop": null,
        "updateContext": null
      },
      "start": 2072,
      "end": 2073,
      "loc": {
        "start": {
          "line": 49,
          "column": 32
        },
        "end": {
          "line": 49,
          "column": 33
        }
      }
    },
    {
      "type": {
        "label": "name",
        "beforeExpr": false,
        "startsExpr": true,
        "rightAssociative": false,
        "isLoop": false,
        "isAssign": false,
        "prefix": false,
        "postfix": false,
        "binop": null
      },
      "value": "api",
      "start": 2073,
      "end": 2076,
      "loc": {
        "start": {
          "line": 49,
          "column": 33
        },
        "end": {
          "line": 49,
          "column": 36
        }
      }
    },
    {
      "type": {
        "label": ",",
        "beforeExpr": true,
        "startsExpr": false,
        "rightAssociative": false,
        "isLoop": false,
        "isAssign": false,
        "prefix": false,
        "postfix": false,
        "binop": null,
        "updateContext": null
      },
      "start": 2076,
      "end": 2077,
      "loc": {
        "start": {
          "line": 49,
          "column": 36
        },
        "end": {
          "line": 49,
          "column": 37
        }
      }
    },
    {
      "type": {
        "label": "this",
        "keyword": "this",
        "beforeExpr": false,
        "startsExpr": true,
        "rightAssociative": false,
        "isLoop": false,
        "isAssign": false,
        "prefix": false,
        "postfix": false,
        "binop": null,
        "updateContext": null
      },
      "value": "this",
      "start": 2078,
      "end": 2082,
      "loc": {
        "start": {
          "line": 49,
          "column": 38
        },
        "end": {
          "line": 49,
          "column": 42
        }
      }
    },
    {
      "type": {
        "label": ")",
        "beforeExpr": false,
        "startsExpr": false,
        "rightAssociative": false,
        "isLoop": false,
        "isAssign": false,
        "prefix": false,
        "postfix": false,
        "binop": null
      },
      "start": 2082,
      "end": 2083,
      "loc": {
        "start": {
          "line": 49,
          "column": 42
        },
        "end": {
          "line": 49,
          "column": 43
        }
      }
    },
    {
      "type": {
        "label": ";",
        "beforeExpr": true,
        "startsExpr": false,
        "rightAssociative": false,
        "isLoop": false,
        "isAssign": false,
        "prefix": false,
        "postfix": false,
        "binop": null,
        "updateContext": null
      },
      "start": 2083,
      "end": 2084,
      "loc": {
        "start": {
          "line": 49,
          "column": 43
        },
        "end": {
          "line": 49,
          "column": 44
        }
      }
    },
    {
      "type": {
        "label": "}",
        "beforeExpr": false,
        "startsExpr": false,
        "rightAssociative": false,
        "isLoop": false,
        "isAssign": false,
        "prefix": false,
        "postfix": false,
        "binop": null
      },
      "start": 2087,
      "end": 2088,
      "loc": {
        "start": {
          "line": 50,
          "column": 2
        },
        "end": {
          "line": 50,
          "column": 3
        }
      }
    },
    {
      "type": {
        "label": "name",
        "beforeExpr": false,
        "startsExpr": true,
        "rightAssociative": false,
        "isLoop": false,
        "isAssign": false,
        "prefix": false,
        "postfix": false,
        "binop": null
      },
      "value": "get",
      "start": 2092,
      "end": 2095,
      "loc": {
        "start": {
          "line": 52,
          "column": 2
        },
        "end": {
          "line": 52,
          "column": 5
        }
      }
    },
    {
      "type": {
        "label": "name",
        "beforeExpr": false,
        "startsExpr": true,
        "rightAssociative": false,
        "isLoop": false,
        "isAssign": false,
        "prefix": false,
        "postfix": false,
        "binop": null
      },
      "value": "resourceName",
      "start": 2096,
      "end": 2108,
      "loc": {
        "start": {
          "line": 52,
          "column": 6
        },
        "end": {
          "line": 52,
          "column": 18
        }
      }
    },
    {
      "type": {
        "label": "(",
        "beforeExpr": true,
        "startsExpr": true,
        "rightAssociative": false,
        "isLoop": false,
        "isAssign": false,
        "prefix": false,
        "postfix": false,
        "binop": null
      },
      "start": 2108,
      "end": 2109,
      "loc": {
        "start": {
          "line": 52,
          "column": 18
        },
        "end": {
          "line": 52,
          "column": 19
        }
      }
    },
    {
      "type": {
        "label": ")",
        "beforeExpr": false,
        "startsExpr": false,
        "rightAssociative": false,
        "isLoop": false,
        "isAssign": false,
        "prefix": false,
        "postfix": false,
        "binop": null
      },
      "start": 2109,
      "end": 2110,
      "loc": {
        "start": {
          "line": 52,
          "column": 19
        },
        "end": {
          "line": 52,
          "column": 20
        }
      }
    },
    {
      "type": {
        "label": "{",
        "beforeExpr": true,
        "startsExpr": true,
        "rightAssociative": false,
        "isLoop": false,
        "isAssign": false,
        "prefix": false,
        "postfix": false,
        "binop": null
      },
      "start": 2111,
      "end": 2112,
      "loc": {
        "start": {
          "line": 52,
          "column": 21
        },
        "end": {
          "line": 52,
          "column": 22
        }
      }
    },
    {
      "type": {
        "label": "return",
        "keyword": "return",
        "beforeExpr": true,
        "startsExpr": false,
        "rightAssociative": false,
        "isLoop": false,
        "isAssign": false,
        "prefix": false,
        "postfix": false,
        "binop": null,
        "updateContext": null
      },
      "value": "return",
      "start": 2117,
      "end": 2123,
      "loc": {
        "start": {
          "line": 53,
          "column": 4
        },
        "end": {
          "line": 53,
          "column": 10
        }
      }
    },
    {
      "type": {
        "label": "string",
        "beforeExpr": false,
        "startsExpr": true,
        "rightAssociative": false,
        "isLoop": false,
        "isAssign": false,
        "prefix": false,
        "postfix": false,
        "binop": null,
        "updateContext": null
      },
      "value": "layers",
      "start": 2124,
      "end": 2132,
      "loc": {
        "start": {
          "line": 53,
          "column": 11
        },
        "end": {
          "line": 53,
          "column": 19
        }
      }
    },
    {
      "type": {
        "label": ";",
        "beforeExpr": true,
        "startsExpr": false,
        "rightAssociative": false,
        "isLoop": false,
        "isAssign": false,
        "prefix": false,
        "postfix": false,
        "binop": null,
        "updateContext": null
      },
      "start": 2132,
      "end": 2133,
      "loc": {
        "start": {
          "line": 53,
          "column": 19
        },
        "end": {
          "line": 53,
          "column": 20
        }
      }
    },
    {
      "type": {
        "label": "}",
        "beforeExpr": false,
        "startsExpr": false,
        "rightAssociative": false,
        "isLoop": false,
        "isAssign": false,
        "prefix": false,
        "postfix": false,
        "binop": null
      },
      "start": 2136,
      "end": 2137,
      "loc": {
        "start": {
          "line": 54,
          "column": 2
        },
        "end": {
          "line": 54,
          "column": 3
        }
      }
    },
    {
      "type": {
        "label": "}",
        "beforeExpr": false,
        "startsExpr": false,
        "rightAssociative": false,
        "isLoop": false,
        "isAssign": false,
        "prefix": false,
        "postfix": false,
        "binop": null
      },
      "start": 2138,
      "end": 2139,
      "loc": {
        "start": {
          "line": 55,
          "column": 0
        },
        "end": {
          "line": 55,
          "column": 1
        }
      }
    },
    {
      "type": {
        "label": "eof",
        "beforeExpr": false,
        "startsExpr": false,
        "rightAssociative": false,
        "isLoop": false,
        "isAssign": false,
        "prefix": false,
        "postfix": false,
        "binop": null,
        "updateContext": null
      },
      "start": 2140,
      "end": 2140,
      "loc": {
        "start": {
          "line": 56,
          "column": 0
        },
        "end": {
          "line": 56,
          "column": 0
        }
      }
    }
  ]
}